soominsomean/__init__.py
soominsomean/lr.py
tests/__init__.py
tests/units/__init__.py
tests/units/test_lr.py
soominsomean-0.1.1.dist-info/METADATA
soominsomean-0.1.1.dist-info/WHEEL
soominsomean-0.1.1.dist-info/top_level.txt
soominsomean-0.1.1.dist-info/RECORD
